collective.patchwatcher-1.0-py3.7-nspkg.pth
collective/patchwatcher/__init__.py
collective/patchwatcher/configure.zcml
collective/patchwatcher/interfaces.py
collective/patchwatcher/script.py
collective/patchwatcher/setuphandlers.py
collective/patchwatcher/testing.py
collective/patchwatcher/profiles/default/metadata.xml
collective/patchwatcher/profiles/default/registry.xml
collective/patchwatcher/tests/__init__.py
collective/patchwatcher/tests/test_robot.py
collective/patchwatcher/tests/test_setup.py
collective/patchwatcher/tests/robot/test_example.robot
collective.patchwatcher-1.0.dist-info/LICENSE.GPL
collective.patchwatcher-1.0.dist-info/LICENSE.rst
collective.patchwatcher-1.0.dist-info/METADATA
collective.patchwatcher-1.0.dist-info/WHEEL
collective.patchwatcher-1.0.dist-info/entry_points.txt
collective.patchwatcher-1.0.dist-info/namespace_packages.txt
collective.patchwatcher-1.0.dist-info/top_level.txt
collective.patchwatcher-1.0.dist-info/RECORD
