Metadata-Version: 2.1
Name: collective.patchwatcher
Version: 1.0
Summary: Patchwatcher is a great companion for maintaining your customizations in Plone.
Home-page: https://github.com/collective/collective.patchwatcher
Author: Paul Grunewald
Author-email: paul.grunewald@tu-dresden.de
License: GPL version 2
Project-URL: PyPI, https://pypi.python.org/pypi/collective.patchwatcher
Project-URL: Source, https://github.com/collective/collective.patchwatcher
Project-URL: Tracker, https://github.com/collective/collective.patchwatcher/issues
Keywords: Python Plone
Platform: UNKNOWN
Classifier: Development Status :: 4 - Beta
Classifier: Environment :: Web Environment
Classifier: Topic :: Software Development :: Quality Assurance
Classifier: Framework :: Plone
Classifier: Framework :: Plone :: Addon
Classifier: Framework :: Plone :: 4.3
Classifier: Framework :: Plone :: 5.3
Classifier: Framework :: Plone :: 6.0
Classifier: Intended Audience :: Developers
Classifier: Programming Language :: Python
Classifier: Programming Language :: Python :: 2.7
Classifier: Programming Language :: Python :: 3.6
Classifier: Programming Language :: Python :: 3.7
Classifier: Programming Language :: Python :: 3.8
Classifier: Programming Language :: Python :: 3.9
Classifier: Operating System :: OS Independent
Classifier: License :: OSI Approved :: GNU General Public License v2 (GPLv2)
Requires-Python: >=2.7
License-File: LICENSE.GPL
License-File: LICENSE.rst
Requires-Dist: setuptools
Provides-Extra: test
Requires-Dist: plone.app.testing ; extra == 'test'
Requires-Dist: plone.testing (>=5.0.0) ; extra == 'test'
Requires-Dist: plone.app.contenttypes ; extra == 'test'
Requires-Dist: plone.app.robotframework[debug] ; extra == 'test'
